LICENSE
README.md
setup.cfg
setup.py
px_client_builder/__init__.py
px_client_builder/client.py
px_client_builder.egg-info/PKG-INFO
px_client_builder.egg-info/SOURCES.txt
px_client_builder.egg-info/dependency_links.txt
px_client_builder.egg-info/requires.txt
px_client_builder.egg-info/top_level.txt